dict2dot/__init__.py
dict2dot-0.1.dist-info/LICENSE
dict2dot-0.1.dist-info/METADATA
dict2dot-0.1.dist-info/WHEEL
dict2dot-0.1.dist-info/top_level.txt
dict2dot-0.1.dist-info/RECORD
