Metadata-Version: 2.1
Name: dict2dot
Version: 0.1
Summary: Python Dictionary to Dot notation (class) package
Home-page: https://github.com/nandoabreu/python-dict2dot
Author: Fernando Abreu
License: UNKNOWN
Platform: UNKNOWN
Classifier: Programming Language :: Python :: 3
Classifier: License :: OSI Approved :: MIT License
Classifier: Operating System :: OS Independent
